TAN/__init__.py
TANHACKER-0.7.dist-info/METADATA
TANHACKER-0.7.dist-info/WHEEL
TANHACKER-0.7.dist-info/top_level.txt
TANHACKER-0.7.dist-info/RECORD
