Metadata-Version: 2.1
Name: TANHACKER
Version: 0.7
Summary: TAN ENCODERS
Author: TANHACKER
Classifier: Programming Language :: Python :: 3
